test/__init__.py
test/ncloud_apikey_sample.py
test/ncloud_cdn_api_sample.py
test/ncloud_iam_role_sample.py
test/ncloud_load_credentials_sample.py
test/ncloud_server_api_sample.py
test/test_v2_api.py
ncloud_sdk-1.1.8.dist-info/LICENSE
ncloud_sdk-1.1.8.dist-info/METADATA
ncloud_sdk-1.1.8.dist-info/WHEEL
ncloud_sdk-1.1.8.dist-info/top_level.txt
ncloud_sdk-1.1.8.dist-info/RECORD
