Metadata-Version: 2.1
Name: ncloud-sdk
Version: 1.1.8
Summary: ncloud-sdk
Home-page: UNKNOWN
License: UNKNOWN
Keywords: ncloud-sdk,ncloud
Platform: UNKNOWN
Requires-Dist: urllib3 (>=1.15)
Requires-Dist: six (>=1.10)
Requires-Dist: certifi
Requires-Dist: python-dateutil
Requires-Dist: ncloud-apikey (>=1.0.5)
Requires-Dist: ncloud-server (>=1.1.2)
Requires-Dist: ncloud-loadbalancer (>=1.1.1)
Requires-Dist: ncloud-autoscaling (>=1.1.1)
Requires-Dist: ncloud-monitoring (>=1.1.6)
Requires-Dist: ncloud-cdn (>=1.1.1)
Requires-Dist: ncloud-clouddb (>=1.1.1)
Requires-Dist: ncloud-vserver (>=1.0.1)
Requires-Dist: ncloud-vnas (>=1.0.1)
Requires-Dist: ncloud-vpc (>=1.0.1)
